my_sort_test.cp311-win_amd64.pyd
my_sort_test-2.0.dist-info/METADATA
my_sort_test-2.0.dist-info/WHEEL
my_sort_test-2.0.dist-info/top_level.txt
my_sort_test-2.0.dist-info/RECORD
