Metadata-Version: 2.1
Name: my_sort_test
Version: 2.0
Summary: Is test upload module
Author: sky
Author-email: sky@sky1218.com
